[
  {
    "id": 1,
    "name": "Kana kebab",
    "description": "Maukasta kanaa tuoreilla vihanneksilla ja kastikkeella.",
    "price": 8.9,
    "category": "Pääruoat",
    "image": "/images/kana_kebab.jpg",
    "popular": true
  },
  {
    "id": 2,
    "name": "Naudanliha kebab",
    "description": "Herkullista naudanlihaa mausteisella kastikkeella.",
    "price": 9.5,
    "category": "Pääruoat",
    "image": "/images/naudanliha_kebab.jpg",
    "popular": true
  },
  {
    "id": 3,
    "name": "Falafel",
    "description": "Kasvisvaihtoehto kikherneistä valmistettuna.",
    "price": 7.9,
    "category": "Pääruoat",
    "image": "/images/falafel.jpg",
    "popular": true
  },
  {
    "id": 4,
    "name": "Kasvis kebab",
    "description": "Maukasta kasvisproteiinia tuoreilla lisukkeilla.",
    "price": 7.5,
    "category": "Pääruoat",
    "image": "/images/kasvis_kebab.jpg",
    "popular": true
  },
  {
    "id": 5,
    "name": "Pizza Margherita",
    "description": "Perinteinen italialainen pizza tomaattikastikkeella ja mozzarellajuustolla.",
    "price": 10.0,
    "category": "Pizzat",
    "image": "/images/pizza_margherita.jpg",
    "popular": true
  },
  {
    "id": 6,
    "name": "Spaghetti Bolognese",
    "description": "Klassinen italialainen pasta-annos naudanlihakastikkeella.",
    "price": 11.5,
    "category": "Pastat",
    "image": "/images/spaghetti_bolognese.jpg",
    "popular": true
  },
  {
    "id": 7,
    "name": "Caesar Salaatti",
    "description": "Rapea salaatti kanan, krutonkien ja parmesaanin kera.",
    "price": 9.0,
    "category": "Salaatit",
    "image": "/images/caesar_salaatti.jpg",
    "popular": true
  }
]
